text_clean/__init__.py
text_clean/text_clean.so
text_clean/data/char_keep.txt
text_clean/data/digital_letter_normal.txt
text_clean/data/t2s_char_project.txt
text_clean/data/t2s_drop_project.txt
text_clean/data/t2s_word_project.txt
text_clean-0.1.5.dist-info/LICENSE
text_clean-0.1.5.dist-info/METADATA
text_clean-0.1.5.dist-info/WHEEL
text_clean-0.1.5.dist-info/top_level.txt
text_clean-0.1.5.dist-info/RECORD
