Metadata-Version: 2.1
Name: text-clean
Version: 0.1.5
Summary: Process text for NLP
Home-page: https://github.com/mikuh/text_clean
Author: geb
Author-email: 853934146@qq.com
License: UNKNOWN
Platform: UNKNOWN
Classifier: Programming Language :: Python :: 3
Classifier: License :: OSI Approved :: MIT License
Classifier: Operating System :: OS Independent
Requires-Python: >=3.6
